countonce/__init__.py
countonce-0.1.0.dist-info/METADATA
countonce-0.1.0.dist-info/WHEEL
countonce-0.1.0.dist-info/top_level.txt
countonce-0.1.0.dist-info/RECORD
