Metadata-Version: 2.1
Name: countonce
Version: 0.1.0
Summary: Wrapper for the countonce API
Home-page: https://github.com/countonce/countonce-python
Author: CountOnce
License: UNKNOWN
Keywords: countonce,api
Platform: UNKNOWN
Requires-Python: >=3.5
Requires-Dist: requests
